pboutil/__init__.py
pboutil/pbofile.py
pboutil/structures.py
pboutil/utils.py
pboutil-0.1.1.dist-info/METADATA
pboutil-0.1.1.dist-info/RECORD
pboutil-0.1.1.dist-info/WHEEL
pboutil-0.1.1.dist-info/top_level.txt
pboutil-0.1.1.dist-info/zip-safe
